alanbal/__init__.py
alanbal/components/__init__.py
alanbal/components/ast.py
alanbal/models/__init__.py
alanbal/models/ast.py
alanbal/models/encoder.py
alanbal/models/layers.py
alanbal/utils/__init__.py
alanbal/utils/constants.py
alanbal/utils/path_resolver.py
alanbal-0.1.1.dist-info/METADATA
alanbal-0.1.1.dist-info/WHEEL
alanbal-0.1.1.dist-info/top_level.txt
alanbal-0.1.1.dist-info/RECORD
