Metadata-Version: 2.1
Name: alanbal
Version: 0.1.1
Summary: Active Learning Module for Bootstrapping Alan
Home-page: https://bitbucket.org/rbcmllab/data_bootstrap/alanbootstrap/master
Author: Keyi Tang
Author-email: keyi.tang@rbc.com
License: UNKNOWN
Platform: UNKNOWN
Classifier: Programming Language :: Python :: 3
Classifier: License :: OSI Approved :: MIT License
Classifier: Operating System :: OS Independent
